{"directed": true, "multigraph": true, "graph": {}, "nodes": [{"size": 400, "pos": [1.4433756729740623, -2.500000000000001], "id": "Flinders Street"}, {"size": 400, "pos": [-1.4433756729740657, -2.4999999999999996], "id": "Southern Cross"}, {"size": 400, "pos": [-2.8867513459481287, 3.5352507957496894e-16], "id": "Flagstaff"}, {"size": 400, "pos": [-1.4433756729740637, 2.5], "id": "Melbourne Central"}, {"size": 400, "pos": [1.4433756729740645, 2.4999999999999996], "id": "Parliament"}, {"size": 600, "pos": [2.8867513459481287, 0.0], "id": "Richmond"}, {"size": 400, "pos": [7.886751345948129, 0.0], "id": "East Richmond"}, {"size": 400, "pos": [12.886751345948129, 0.0], "id": "Burnley"}, {"size": 300, "pos": [17.886751345948127, 0.0], "id": "Hawthorn"}, {"size": 300, "pos": [22.886751345948127, 0.0], "id": "Glenferrie"}, {"size": 300, "pos": [27.886751345948127, 0.0], "id": "Auburn"}, {"size": 300, "pos": [32.88675134594813, 0.0], "id": "Camberwell"}, {"size": 200, "pos": [37.88675134594813, 0.0], "id": "East Camberwell"}, {"size": 200, "pos": [42.88675134594813, 0.0], "id": "Canterbury"}, {"size": 200, "pos": [47.88675134594813, 0.0], "id": "Chatham"}, {"size": 200, "pos": [52.88675134594813, 0.0], "id": "Union"}, {"size": 200, "pos": [57.88675134594813, 0.0], "id": "Box Hill"}, {"size": 200, "pos": [62.88675134594813, 0.0], "id": "Laburnum"}, {"size": 200, "pos": [67.88675134594813, 0.0], "id": "Blackburn"}, {"size": 200, "pos": [72.88675134594813, 0.0], "id": "Nunawading"}, {"size": 200, "pos": [77.88675134594813, 0.0], "id": "Mitcham"}, {"size": 200, "pos": [82.88675134594813, 0.0], "id": "Heatherdale"}, {"size": 200, "pos": [87.88675134594813, 0.0], "id": "Ringwood"}, {"size": 100, "pos": [92.6420339274239, -1.545084971874737], "id": "Ringwood East"}, {"size": 100, "pos": [97.39731650889966, -3.090169943749474], "id": "Croydon"}, {"size": 100, "pos": [102.15259909037543, -4.635254915624211], "id": "Mooroolbark"}, {"size": 50, "pos": [106.9078816718512, -6.180339887498948], "id": "Lilydale"}, {"size": 100, "pos": [92.88675134594813, 0.0], "id": "Heathmont"}, {"size": 100, "pos": [97.88675134594813, 0.0], "id": "Bayswater"}, {"size": 100, "pos": [102.88675134594813, 0.0], "id": "Boronia"}, {"size": 100, "pos": [107.88675134594813, 0.0], "id": "Ferntree Gully"}, {"size": 100, "pos": [112.88675134594813, 0.0], "id": "Upper Ferntree Gully"}, {"size": 100, "pos": [117.88675134594813, 0.0], "id": "Upwey"}, {"size": 100, "pos": [122.88675134594813, 0.0], "id": "Tecoma"}, {"size": 50, "pos": [127.88675134594813, 0.0], "id": "Belgrave"}, {"size": 100, "pos": [37.21687836487032, -2.5], "id": "Riversdale"}, {"size": 100, "pos": [41.54700538379251, -5.0], "id": "Wilison"}, {"size": 100, "pos": [45.8771324027147, -7.5], "id": "Hartwell"}, {"size": 100, "pos": [50.20725942163689, -10.0], "id": "Burwood"}, {"size": 100, "pos": [54.53738644055908, -12.5], "id": "Ashburton"}, {"size": 50, "pos": [58.86751345948127, -15.0], "id": "Alamein"}, {"size": 100, "pos": [16.422285251880865, -3.5355339059327373], "id": "Heyington"}, {"size": 100, "pos": [19.957819157813603, -7.071067811865475], "id": "Kooyong"}, {"size": 100, "pos": [23.49335306374634, -10.606601717798211], "id": "Tooronga"}, {"size": 100, "pos": [27.02888696967908, -14.14213562373095], "id": "Gardiner"}, {"size": 100, "pos": [30.564420875611816, -17.677669529663685], "id": "Glen Iris"}, {"size": 100, "pos": [34.099954781544554, -21.213203435596423], "id": "Darling"}, {"size": 100, "pos": [37.63548868747729, -24.74873734152916], "id": "East Malvern"}, {"size": 100, "pos": [41.17102259341003, -28.2842712474619], "id": "Holmesglen"}, {"size": 100, "pos": [44.70655649934277, -31.819805153394636], "id": "Jordanville"}, {"size": 100, "pos": [48.242090405275505, -35.35533905932737], "id": "Mount Waverley"}, {"size": 100, "pos": [51.77762431120824, -38.89087296526011], "id": "Syndal"}, {"size": 50, "pos": [55.31315821714098, -42.426406871192846], "id": "Glen Waverley"}], "links": [{"color": "lightblue", "source": "Flinders Street", "target": "Southern Cross", "key": 0}, {"color": "cyan", "source": "Flinders Street", "target": "Southern Cross", "key": 1}, {"color": "blue", "source": "Flinders Street", "target": "Southern Cross", "key": 2}, {"color": "darkblue", "source": "Flinders Street", "target": "Southern Cross", "key": 3}, {"color": "lightblue", "source": "Flinders Street", "target": "Richmond", "key": 0}, {"color": "cyan", "source": "Flinders Street", "target": "Richmond", "key": 1}, {"color": "blue", "source": "Flinders Street", "target": "Richmond", "key": 2}, {"color": "darkblue", "source": "Flinders Street", "target": "Richmond", "key": 3}, {"color": "lightblue", "source": "Southern Cross", "target": "Flagstaff", "key": 0}, {"color": "cyan", "source": "Southern Cross", "target": "Flagstaff", "key": 1}, {"color": "blue", "source": "Southern Cross", "target": "Flagstaff", "key": 2}, {"color": "darkblue", "source": "Southern Cross", "target": "Flagstaff", "key": 3}, {"color": "lightblue", "source": "Southern Cross", "target": "Flinders Street", "key": 0}, {"color": "cyan", "source": "Southern Cross", "target": "Flinders Street", "key": 1}, {"color": "blue", "source": "Southern Cross", "target": "Flinders Street", "key": 2}, {"color": "darkblue", "source": "Southern Cross", "target": "Flinders Street", "key": 3}, {"color": "lightblue", "source": "Flagstaff", "target": "Melbourne Central", "key": 0}, {"color": "cyan", "source": "Flagstaff", "target": "Melbourne Central", "key": 1}, {"color": "blue", "source": "Flagstaff", "target": "Melbourne Central", "key": 2}, {"color": "darkblue", "source": "Flagstaff", "target": "Melbourne Central", "key": 3}, {"color": "lightblue", "source": "Flagstaff", "target": "Southern Cross", "key": 0}, {"color": "cyan", "source": "Flagstaff", "target": "Southern Cross", "key": 1}, {"color": "blue", "source": "Flagstaff", "target": "Southern Cross", "key": 2}, {"color": "darkblue", "source": "Flagstaff", "target": "Southern Cross", "key": 3}, {"color": "lightblue", "source": "Melbourne Central", "target": "Parliament", "key": 0}, {"color": "cyan", "source": "Melbourne Central", "target": "Parliament", "key": 1}, {"color": "blue", "source": "Melbourne Central", "target": "Parliament", "key": 2}, {"color": "darkblue", "source": "Melbourne Central", "target": "Parliament", "key": 3}, {"color": "lightblue", "source": "Melbourne Central", "target": "Flagstaff", "key": 0}, {"color": "cyan", "source": "Melbourne Central", "target": "Flagstaff", "key": 1}, {"color": "blue", "source": "Melbourne Central", "target": "Flagstaff", "key": 2}, {"color": "darkblue", "source": "Melbourne Central", "target": "Flagstaff", "key": 3}, {"color": "lightblue", "source": "Parliament", "target": "Richmond", "key": 0}, {"color": "cyan", "source": "Parliament", "target": "Richmond", "key": 1}, {"color": "blue", "source": "Parliament", "target": "Richmond", "key": 2}, {"color": "darkblue", "source": "Parliament", "target": "Richmond", "key": 3}, {"color": "lightblue", "source": "Parliament", "target": "Melbourne Central", "key": 0}, {"color": "cyan", "source": "Parliament", "target": "Melbourne Central", "key": 1}, {"color": "blue", "source": "Parliament", "target": "Melbourne Central", "key": 2}, {"color": "darkblue", "source": "Parliament", "target": "Melbourne Central", "key": 3}, {"color": "lightblue", "source": "Richmond", "target": "East Richmond", "key": 0}, {"color": "cyan", "source": "Richmond", "target": "East Richmond", "key": 1}, {"color": "blue", "source": "Richmond", "target": "East Richmond", "key": 2}, {"color": "darkblue", "source": "Richmond", "target": "East Richmond", "key": 3}, {"color": "lightblue", "source": "Richmond", "target": "Parliament", "key": 0}, {"color": "cyan", "source": "Richmond", "target": "Parliament", "key": 1}, {"color": "blue", "source": "Richmond", "target": "Parliament", "key": 2}, {"color": "darkblue", "source": "Richmond", "target": "Parliament", "key": 3}, {"color": "lightblue", "source": "Richmond", "target": "Flinders Street", "key": 0}, {"color": "cyan", "source": "Richmond", "target": "Flinders Street", "key": 1}, {"color": "blue", "source": "Richmond", "target": "Flinders Street", "key": 2}, {"color": "darkblue", "source": "Richmond", "target": "Flinders Street", "key": 3}, {"color": "lightblue", "source": "East Richmond", "target": "Burnley", "key": 0}, {"color": "cyan", "source": "East Richmond", "target": "Burnley", "key": 1}, {"color": "blue", "source": "East Richmond", "target": "Burnley", "key": 2}, {"color": "darkblue", "source": "East Richmond", "target": "Burnley", "key": 3}, {"color": "lightblue", "source": "East Richmond", "target": "Richmond", "key": 0}, {"color": "cyan", "source": "East Richmond", "target": "Richmond", "key": 1}, {"color": "blue", "source": "East Richmond", "target": "Richmond", "key": 2}, {"color": "darkblue", "source": "East Richmond", "target": "Richmond", "key": 3}, {"color": "lightblue", "source": "Burnley", "target": "Hawthorn", "key": 0}, {"color": "cyan", "source": "Burnley", "target": "Hawthorn", "key": 1}, {"color": "blue", "source": "Burnley", "target": "Hawthorn", "key": 2}, {"color": "lightblue", "source": "Burnley", "target": "East Richmond", "key": 0}, {"color": "cyan", "source": "Burnley", "target": "East Richmond", "key": 1}, {"color": "blue", "source": "Burnley", "target": "East Richmond", "key": 2}, {"color": "darkblue", "source": "Burnley", "target": "East Richmond", "key": 3}, {"color": "darkblue", "source": "Burnley", "target": "Heyington", "key": 3}, {"color": "lightblue", "source": "Hawthorn", "target": "Glenferrie", "key": 0}, {"color": "cyan", "source": "Hawthorn", "target": "Glenferrie", "key": 1}, {"color": "blue", "source": "Hawthorn", "target": "Glenferrie", "key": 2}, {"color": "lightblue", "source": "Hawthorn", "target": "Burnley", "key": 0}, {"color": "cyan", "source": "Hawthorn", "target": "Burnley", "key": 1}, {"color": "blue", "source": "Hawthorn", "target": "Burnley", "key": 2}, {"color": "lightblue", "source": "Glenferrie", "target": "Auburn", "key": 0}, {"color": "cyan", "source": "Glenferrie", "target": "Auburn", "key": 1}, {"color": "blue", "source": "Glenferrie", "target": "Auburn", "key": 2}, {"color": "lightblue", "source": "Glenferrie", "target": "Hawthorn", "key": 0}, {"color": "cyan", "source": "Glenferrie", "target": "Hawthorn", "key": 1}, {"color": "blue", "source": "Glenferrie", "target": "Hawthorn", "key": 2}, {"color": "lightblue", "source": "Auburn", "target": "Camberwell", "key": 0}, {"color": "cyan", "source": "Auburn", "target": "Camberwell", "key": 1}, {"color": "blue", "source": "Auburn", "target": "Camberwell", "key": 2}, {"color": "lightblue", "source": "Auburn", "target": "Glenferrie", "key": 0}, {"color": "cyan", "source": "Auburn", "target": "Glenferrie", "key": 1}, {"color": "blue", "source": "Auburn", "target": "Glenferrie", "key": 2}, {"color": "lightblue", "source": "Camberwell", "target": "East Camberwell", "key": 0}, {"color": "cyan", "source": "Camberwell", "target": "East Camberwell", "key": 1}, {"color": "lightblue", "source": "Camberwell", "target": "Auburn", "key": 0}, {"color": "cyan", "source": "Camberwell", "target": "Auburn", "key": 1}, {"color": "blue", "source": "Camberwell", "target": "Auburn", "key": 2}, {"color": "blue", "source": "Camberwell", "target": "Riversdale", "key": 2}, {"color": "lightblue", "source": "East Camberwell", "target": "Canterbury", "key": 0}, {"color": "cyan", "source": "East Camberwell", "target": "Canterbury", "key": 1}, {"color": "lightblue", "source": "East Camberwell", "target": "Camberwell", "key": 0}, {"color": "cyan", "source": "East Camberwell", "target": "Camberwell", "key": 1}, {"color": "lightblue", "source": "Canterbury", "target": "Chatham", "key": 0}, {"color": "cyan", "source": "Canterbury", "target": "Chatham", "key": 1}, {"color": "lightblue", "source": "Canterbury", "target": "East Camberwell", "key": 0}, {"color": "cyan", "source": "Canterbury", "target": "East Camberwell", "key": 1}, {"color": "lightblue", "source": "Chatham", "target": "Union", "key": 0}, {"color": "cyan", "source": "Chatham", "target": "Union", "key": 1}, {"color": "lightblue", "source": "Chatham", "target": "Canterbury", "key": 0}, {"color": "cyan", "source": "Chatham", "target": "Canterbury", "key": 1}, {"color": "lightblue", "source": "Union", "target": "Box Hill", "key": 0}, {"color": "cyan", "source": "Union", "target": "Box Hill", "key": 1}, {"color": "lightblue", "source": "Union", "target": "Chatham", "key": 0}, {"color": "cyan", "source": "Union", "target": "Chatham", "key": 1}, {"color": "lightblue", "source": "Box Hill", "target": "Laburnum", "key": 0}, {"color": "cyan", "source": "Box Hill", "target": "Laburnum", "key": 1}, {"color": "lightblue", "source": "Box Hill", "target": "Union", "key": 0}, {"color": "cyan", "source": "Box Hill", "target": "Union", "key": 1}, {"color": "lightblue", "source": "Laburnum", "target": "Blackburn", "key": 0}, {"color": "cyan", "source": "Laburnum", "target": "Blackburn", "key": 1}, {"color": "lightblue", "source": "Laburnum", "target": "Box Hill", "key": 0}, {"color": "cyan", "source": "Laburnum", "target": "Box Hill", "key": 1}, {"color": "lightblue", "source": "Blackburn", "target": "Nunawading", "key": 0}, {"color": "cyan", "source": "Blackburn", "target": "Nunawading", "key": 1}, {"color": "lightblue", "source": "Blackburn", "target": "Laburnum", "key": 0}, {"color": "cyan", "source": "Blackburn", "target": "Laburnum", "key": 1}, {"color": "lightblue", "source": "Nunawading", "target": "Mitcham", "key": 0}, {"color": "cyan", "source": "Nunawading", "target": "Mitcham", "key": 1}, {"color": "lightblue", "source": "Nunawading", "target": "Blackburn", "key": 0}, {"color": "cyan", "source": "Nunawading", "target": "Blackburn", "key": 1}, {"color": "lightblue", "source": "Mitcham", "target": "Heatherdale", "key": 0}, {"color": "cyan", "source": "Mitcham", "target": "Heatherdale", "key": 1}, {"color": "lightblue", "source": "Mitcham", "target": "Nunawading", "key": 0}, {"color": "cyan", "source": "Mitcham", "target": "Nunawading", "key": 1}, {"color": "lightblue", "source": "Heatherdale", "target": "Ringwood", "key": 0}, {"color": "cyan", "source": "Heatherdale", "target": "Ringwood", "key": 1}, {"color": "lightblue", "source": "Heatherdale", "target": "Mitcham", "key": 0}, {"color": "cyan", "source": "Heatherdale", "target": "Mitcham", "key": 1}, {"color": "lightblue", "source": "Ringwood", "target": "Ringwood East", "key": 0}, {"color": "lightblue", "source": "Ringwood", "target": "Heatherdale", "key": 0}, {"color": "cyan", "source": "Ringwood", "target": "Heatherdale", "key": 1}, {"color": "cyan", "source": "Ringwood", "target": "Heathmont", "key": 1}, {"color": "lightblue", "source": "Ringwood East", "target": "Croydon", "key": 0}, {"color": "lightblue", "source": "Ringwood East", "target": "Ringwood", "key": 0}, {"color": "lightblue", "source": "Croydon", "target": "Mooroolbark", "key": 0}, {"color": "lightblue", "source": "Croydon", "target": "Ringwood East", "key": 0}, {"color": "lightblue", "source": "Mooroolbark", "target": "Lilydale", "key": 0}, {"color": "lightblue", "source": "Mooroolbark", "target": "Croydon", "key": 0}, {"color": "lightblue", "source": "Lilydale", "target": "Mooroolbark", "key": 0}, {"color": "cyan", "source": "Heathmont", "target": "Bayswater", "key": 1}, {"color": "cyan", "source": "Heathmont", "target": "Ringwood", "key": 1}, {"color": "cyan", "source": "Bayswater", "target": "Boronia", "key": 1}, {"color": "cyan", "source": "Bayswater", "target": "Heathmont", "key": 1}, {"color": "cyan", "source": "Boronia", "target": "Ferntree Gully", "key": 1}, {"color": "cyan", "source": "Boronia", "target": "Bayswater", "key": 1}, {"color": "cyan", "source": "Ferntree Gully", "target": "Upper Ferntree Gully", "key": 1}, {"color": "cyan", "source": "Ferntree Gully", "target": "Boronia", "key": 1}, {"color": "cyan", "source": "Upper Ferntree Gully", "target": "Upwey", "key": 1}, {"color": "cyan", "source": "Upper Ferntree Gully", "target": "Ferntree Gully", "key": 1}, {"color": "cyan", "source": "Upwey", "target": "Tecoma", "key": 1}, {"color": "cyan", "source": "Upwey", "target": "Upper Ferntree Gully", "key": 1}, {"color": "cyan", "source": "Tecoma", "target": "Belgrave", "key": 1}, {"color": "cyan", "source": "Tecoma", "target": "Upwey", "key": 1}, {"color": "cyan", "source": "Belgrave", "target": "Tecoma", "key": 1}, {"color": "blue", "source": "Riversdale", "target": "Wilison", "key": 2}, {"color": "blue", "source": "Riversdale", "target": "Camberwell", "key": 2}, {"color": "blue", "source": "Wilison", "target": "Hartwell", "key": 2}, {"color": "blue", "source": "Wilison", "target": "Riversdale", "key": 2}, {"color": "blue", "source": "Hartwell", "target": "Burwood", "key": 2}, {"color": "blue", "source": "Hartwell", "target": "Wilison", "key": 2}, {"color": "blue", "source": "Burwood", "target": "Ashburton", "key": 2}, {"color": "blue", "source": "Burwood", "target": "Hartwell", "key": 2}, {"color": "blue", "source": "Ashburton", "target": "Alamein", "key": 2}, {"color": "blue", "source": "Ashburton", "target": "Burwood", "key": 2}, {"color": "blue", "source": "Alamein", "target": "Ashburton", "key": 2}, {"color": "darkblue", "source": "Heyington", "target": "Kooyong", "key": 3}, {"color": "darkblue", "source": "Heyington", "target": "Burnley", "key": 3}, {"color": "darkblue", "source": "Kooyong", "target": "Tooronga", "key": 3}, {"color": "darkblue", "source": "Kooyong", "target": "Heyington", "key": 3}, {"color": "darkblue", "source": "Tooronga", "target": "Gardiner", "key": 3}, {"color": "darkblue", "source": "Tooronga", "target": "Kooyong", "key": 3}, {"color": "darkblue", "source": "Gardiner", "target": "Glen Iris", "key": 3}, {"color": "darkblue", "source": "Gardiner", "target": "Tooronga", "key": 3}, {"color": "darkblue", "source": "Glen Iris", "target": "Darling", "key": 3}, {"color": "darkblue", "source": "Glen Iris", "target": "Gardiner", "key": 3}, {"color": "darkblue", "source": "Darling", "target": "East Malvern", "key": 3}, {"color": "darkblue", "source": "Darling", "target": "Glen Iris", "key": 3}, {"color": "darkblue", "source": "East Malvern", "target": "Holmesglen", "key": 3}, {"color": "darkblue", "source": "East Malvern", "target": "Darling", "key": 3}, {"color": "darkblue", "source": "Holmesglen", "target": "Jordanville", "key": 3}, {"color": "darkblue", "source": "Holmesglen", "target": "East Malvern", "key": 3}, {"color": "darkblue", "source": "Jordanville", "target": "Mount Waverley", "key": 3}, {"color": "darkblue", "source": "Jordanville", "target": "Holmesglen", "key": 3}, {"color": "darkblue", "source": "Mount Waverley", "target": "Syndal", "key": 3}, {"color": "darkblue", "source": "Mount Waverley", "target": "Jordanville", "key": 3}, {"color": "darkblue", "source": "Syndal", "target": "Glen Waverley", "key": 3}, {"color": "darkblue", "source": "Syndal", "target": "Mount Waverley", "key": 3}, {"color": "darkblue", "source": "Glen Waverley", "target": "Syndal", "key": 3}]}